{
  "name": "NEOFlowOFF",
  "symbol": "NEOFLW",
  "status": "canonical",
  "chain": {
    "name": "Base",
    "network": "mainnet",
    "chainId": 8453,
    "explorer": "https://basescan.org"
  },
  "contract": {
    "address": "0x41f4ff3d45ded9c1332e4908f637b75fe83f5d6b",
    "decimals": 18,
    "links": {
      "token": "https://basescan.org/address/0x41f4ff3d45ded9c1332e4908f637b75fe83f5d6b#code"
    },
    "source": {
      "factory": "NEO SMART FACTORY v0.5.3",
      "repo": "https://www.nsfactory.xyz",
      "maintainer": "NEO Protocol (team@neosmart.factory)",
      "attribution": "Powered by NEO SMART FACTORY"
    }
  },
  "usage": [
    "workspace-token",
    "gamificacao",
    "neo-flowoff"
  ],
  "notes": [
    "Canonical token for NEØ-FlowOFF ecosystem <https://www.neoflowoff.agency> . Base mainnet deployment via NEØ SMART FACTORY."
  ]
}
